awiki/__init__.py
awiki/client.py
awiki/constants.py
awiki/models/enums.py
awiki/models/internal.py
awiki/models/results.py
awiki-1.0.3.dist-info/LICENSE
awiki-1.0.3.dist-info/METADATA
awiki-1.0.3.dist-info/WHEEL
awiki-1.0.3.dist-info/RECORD
