Metadata-Version: 2.1
Name: awiki
Version: 1.0.3
Summary: A basic asynchronous wrapper for the WikiMedia API
Author: statikana
Author-email: contact@statikana.dev
Requires-Python: >=3.9,<4.0
Classifier: Programming Language :: Python :: 3
Classifier: Programming Language :: Python :: 3.9
Classifier: Programming Language :: Python :: 3.10
Classifier: Programming Language :: Python :: 3.11
Classifier: Programming Language :: Python :: 3.12
Requires-Dist: httpx (>=0.27.0,<0.28.0)
